SimpleFlaskLogger/__init__.py
SimpleFlaskLogger/logger.py
simple_flask_logger-0.2.dist-info/LICENSE
simple_flask_logger-0.2.dist-info/METADATA
simple_flask_logger-0.2.dist-info/WHEEL
simple_flask_logger-0.2.dist-info/top_level.txt
simple_flask_logger-0.2.dist-info/RECORD
